{"total":3,"result":[{"PostID":"554442158510841945","Title":"The Walking Dead S02E08: Nebraska","Url":"http://videodir.blogspot.com/2016/11/nonton-film-walking-dead-s02e08.html","ImageUrl":"https://3.bp.blogspot.com/-Zr1PNH8XNGw/WBrY_gtvX6I/AAAAAAAAD0M/VqOAPzCd610LnH337-FiW6BLkuKB5elUgCLcB/w300-h400-c/The%2BWalking%2BDead%2BS02E08%2B-%2BNebraska%2B%25282012%2529%2B-%2B02.jpg","MostViewed":0.0,"Labels":"(2011), Drama, Horror, Sci-Fi, The Walking Dead, The Walking Dead Season 2, Thriller"},{"PostID":"376154962457733690","Title":"The Walking Dead S02E05: Chupacabra","Url":"http://videodir.blogspot.com/2016/11/nonton-film-walking-dead-s02e05.html","ImageUrl":"https://4.bp.blogspot.com/-TTVqPPdqOsI/WBrWJEAZ-mI/AAAAAAAADzs/o5HieAAagfU3Cp7SLqFQodXDPP_7gP5lQCLcB/w300-h400-c/The%2BWalking%2BDead%2BS02E05%2B-%2BChupacabra%2B%25282011%2529%2B-%2B01.jpg","MostViewed":0.0,"Labels":"(2011), Drama, Horror, Sci-Fi, The Walking Dead, The Walking Dead Season 2, Thriller"},{"PostID":"5814206582095317982","Title":"Friends with Benefits","Url":"http://www.fishcake.co.id/2015/10/nonton-film-friends-with-benefits-2011.html","ImageUrl":"https://2.bp.blogspot.com/-Po-kfNJwS4M/VjMN5FXWmNI/AAAAAAAABIQ/POTX0bkkbTk/w300-h400-c/Friends%2Bwith%2BBenefits%2B%25282011%2529%2B-%2B03a.jpg","MostViewed":11.0,"Labels":"(2011), Comedy, Romance"},{"PostID":"1064954776401448757","Title":"The Walking Dead S02E10: 18 Miles Out","Url":"http://videodir.blogspot.com/2016/11/nonton-film-walking-dead-s02e10-18.html","ImageUrl":"https://4.bp.blogspot.com/-L_JKKy9tIZo/WBrcZLSunjI/AAAAAAAAD0k/1visAG5nESIPKJdLBrZgyDNKKjqbjOgbQCLcB/w300-h400-c/The%2BWalking%2BDead%2BS02E10%2B-%2B18%2BMiles%2BOut%2B%25282012%2529%2B-%2B11.jpg","MostViewed":0.0,"Labels":"(2011), Drama, Horror, Sci-Fi, The Walking Dead, The Walking Dead Season 2, Thriller"}]}